{
  "$schema": "https://json-schema.org/draft/2020-12/schema",
  "title": "Ontological Assertion",
  "description": "RDF triple constrained to values in the RFK Assassination Case Reasoning ontology",
  "type": "object",
  "required": [
    "subject",
    "predicate",
    "object",
    "confidence"
  ],
  "additionalProperties": false,
  "properties": {
    "subject": {
      "type": "string",
      "enum": [
        "Person",
        "PhysicalEvidence",
        "TestimonialEvidence",
        "ForensicFinding",
        "DocumentaryEvidence",
        "LegalProceeding",
        "LegalArgument",
        "Contradiction",
        "Claim",
        "Verdict",
        "Location",
        "Event",
        "EvidenceAssessment",
        "RobertFKennedy",
        "SirhanSirhan",
        "ThomasNoguchi",
        "KarlUecker",
        "ThaneEugeneCesar",
        "PaulSchrade",
        "DeWayneWolfer",
        "WilliamHarper",
        "LawrenceLessig",
        "GrantCooper",
        "VincentBugliosi",
        "IverJohnsonRevolver",
        "BulletFragmentsVictim",
        "BulletFragmentsBystanders",
        "DoorFrameBullets",
        "PowderBurnPatterns",
        "UeckerTestimony",
        "CesarTestimony",
        "WitnessConsensus",
        "SchradeTestimony",
        "AutopsyFinding_ShotDirection",
        "AutopsyFinding_MuzzleDistance",
        "AutopsyFinding_FatalShot",
        "AutopsyFinding_ThreeHits",
        "BulletCountAnalysis",
        "WolferBallisticsReport",
        "HarperBallisticsChallenge",
        "PowderBurnAnalysis",
        "NoguchisAutopsyReport",
        "LAPDInvestigationFiles",
        "TrialTranscripts",
        "LessigChatGPTExperiment",
        "PeopleVSirhan1969",
        "ParoleHearings",
        "ReinvestigationPetitions",
        "Argument_OfficialNarrative",
        "Argument_SecondGunHypothesis",
        "Argument_EvidenceIntegrity",
        "Argument_LessigReasoning",
        "Contradiction_DirectionOfFire",
        "Contradiction_MuzzleDistance",
        "Contradiction_BulletCount",
        "Contradiction_BallisticsMismatch",
        "Claim_SirhanSoleShooter",
        "Claim_SirhanFiredFromFront",
        "Claim_ShotsFromBehind",
        "Claim_SecondGunman",
        "Claim_MoreThan8Bullets",
        "Claim_ContactRange",
        "Claim_SirhanDistance",
        "Verdict_SirhanGuilty",
        "Verdict_DeathSentence",
        "AmbassadorHotel",
        "AmbassadorHotelPantry",
        "RFKShootingEvent",
        "CaliforniaPrimaryVictorySpeech",
        "Assessment_AutopsyVsWitnesses",
        "Assessment_StructuredFactsVsLLM",
        "Assessment_CesarPosition"
      ],
      "description": "Subject identifier in the ontology"
    },
    "predicate": {
      "type": "string",
      "enum": [
        "accusedOf",
        "attestedBy",
        "challengedBy",
        "composedOf",
        "consistentWith",
        "contradicts",
        "convictedIn",
        "defendedBy",
        "documentedIn",
        "groundedIn",
        "identifiedBy",
        "inconsistentWith",
        "instanceOf",
        "involvedIn",
        "locatedAt",
        "performedBy",
        "presentedIn",
        "prosecutedBy",
        "resultsIn",
        "supports"
      ],
      "description": "Relation predicate"
    },
    "object": {
      "type": "string",
      "enum": [
        "Person",
        "PhysicalEvidence",
        "TestimonialEvidence",
        "ForensicFinding",
        "DocumentaryEvidence",
        "LegalProceeding",
        "LegalArgument",
        "Contradiction",
        "Claim",
        "Verdict",
        "Location",
        "Event",
        "EvidenceAssessment",
        "RobertFKennedy",
        "SirhanSirhan",
        "ThomasNoguchi",
        "KarlUecker",
        "ThaneEugeneCesar",
        "PaulSchrade",
        "DeWayneWolfer",
        "WilliamHarper",
        "LawrenceLessig",
        "GrantCooper",
        "VincentBugliosi",
        "IverJohnsonRevolver",
        "BulletFragmentsVictim",
        "BulletFragmentsBystanders",
        "DoorFrameBullets",
        "PowderBurnPatterns",
        "UeckerTestimony",
        "CesarTestimony",
        "WitnessConsensus",
        "SchradeTestimony",
        "AutopsyFinding_ShotDirection",
        "AutopsyFinding_MuzzleDistance",
        "AutopsyFinding_FatalShot",
        "AutopsyFinding_ThreeHits",
        "BulletCountAnalysis",
        "WolferBallisticsReport",
        "HarperBallisticsChallenge",
        "PowderBurnAnalysis",
        "NoguchisAutopsyReport",
        "LAPDInvestigationFiles",
        "TrialTranscripts",
        "LessigChatGPTExperiment",
        "PeopleVSirhan1969",
        "ParoleHearings",
        "ReinvestigationPetitions",
        "Argument_OfficialNarrative",
        "Argument_SecondGunHypothesis",
        "Argument_EvidenceIntegrity",
        "Argument_LessigReasoning",
        "Contradiction_DirectionOfFire",
        "Contradiction_MuzzleDistance",
        "Contradiction_BulletCount",
        "Contradiction_BallisticsMismatch",
        "Claim_SirhanSoleShooter",
        "Claim_SirhanFiredFromFront",
        "Claim_ShotsFromBehind",
        "Claim_SecondGunman",
        "Claim_MoreThan8Bullets",
        "Claim_ContactRange",
        "Claim_SirhanDistance",
        "Verdict_SirhanGuilty",
        "Verdict_DeathSentence",
        "AmbassadorHotel",
        "AmbassadorHotelPantry",
        "RFKShootingEvent",
        "CaliforniaPrimaryVictorySpeech",
        "Assessment_AutopsyVsWitnesses",
        "Assessment_StructuredFactsVsLLM",
        "Assessment_CesarPosition"
      ],
      "description": "Object identifier in the ontology"
    },
    "confidence": {
      "type": "number",
      "minimum": 0.0,
      "maximum": 1.0,
      "description": "Assertion confidence score (0.0 to 1.0)"
    },
    "grounded_in_wikidata": {
      "type": "boolean",
      "description": "Is the assertion verifiable on Wikidata?"
    }
  }
}